{
  "username": "Логин",
  "password": "Пароль",
	
  "register_title": "Регистрация",
  "register_header": "Регистрация на «{{.name}}»",
  "register_button": "Зарегистрироваться",
  
  "login_title": "Вход",
	"login_header": "Вход в «{{.name}}»",
	"login_button": "Войти",
	"login_oidc_button": "Войти через ",

  "logout_title": "Выйти?",
	"logout_header": "Выйти?",
	"logout_button": "Подтвердить",
	"logout_anon": "Вы не можете выйти, потому что ещё не вошли.",
	
  "lock_title": "Доступ закрыт",
  
  "password_tip": "Сервер хранит ваш пароль в зашифрованном виде, даже администраторы не смогут его прочесть.",
  "cookie_tip": "Отправляя эту форму, вы разрешаете вики хранить cookie в вашем браузере. Это позволит движку связывать ваши правки с вашей учётной записью. Вы будете авторизованы, пока не выйдете из учётной записи.",
  "telegram_tip": "Вы можете войти с помощью Телеграм. Это сработает, если у вашего профиля есть @имя, и оно не занято в этой вики.",
  
  "noauth": "Аутентификация отключена. Вы можете делать правки анонимно.",
  "noregister": "Регистрация в текущее время недоступна. Администраторы могут вручную создать вам учётную запись, свяжитесь с ними.",

  "error_username": "Неизвестное имя пользователя.",
  "error_password": "Неверный пароль.",
  "error_telegram": "Не удалось авторизоваться через Телеграм.",
  "error_oidc": "Не удалось авторизоваться через OIDC.",

  "go_back": "Назад",
  "go_home": "Домой",
	"go_login": "На страницу входа",
  "try_again": "Ещё раз"
}
